tetris/__init__.py
tetris/engine/__init__.py
tetris/engine/abcs.py
tetris/engine/gravity.py
tetris/engine/queue.py
tetris/engine/rotation.py
tetris/engine/scorer.py
tetris/game.py
tetris/py.typed
tetris/types.py
tetris-0.6.0.dist-info/LICENSE
tetris-0.6.0.dist-info/WHEEL
tetris-0.6.0.dist-info/METADATA
tetris-0.6.0.dist-info/RECORD
