Metadata-Version: 2.1
Name: tetris
Version: 0.6.0
Summary: Simple and modular tetris library
Home-page: https://github.com/dzshn/python-tetris
License: MIT
Keywords: tetris,stacker
Author: Sofia "dzshn" N. L.
Author-email: zshn@pm.me
Requires-Python: >=3.9,<3.11
Classifier: Development Status :: 4 - Beta
Classifier: Intended Audience :: Developers
Classifier: Intended Audience :: Science/Research
Classifier: License :: OSI Approved :: MIT License
Classifier: Operating System :: OS Independent
Classifier: Programming Language :: Python :: 3
Classifier: Programming Language :: Python :: 3.10
Classifier: Programming Language :: Python :: 3.9
Classifier: Topic :: Games/Entertainment
Classifier: Topic :: Software Development :: Libraries :: Python Modules
Classifier: Typing :: Typed
Provides-Extra: docs
Requires-Dist: Sphinx (>=4.4.0,<5.0.0); extra == "docs"
Requires-Dist: furo (>=2022.3.4,<2023.0.0); extra == "docs"
Requires-Dist: numpy (>=1.21.4,<2.0.0)
Requires-Dist: numpydoc (>=1.2,<2.0); extra == "docs"
Requires-Dist: typing-extensions (>=4.0.1,<5.0.0)
Project-URL: Documentation, https://python-tetris.readthedocs.io/
Project-URL: Repository, https://github.com/dzshn/python-tetris
